devart/bigcommerce/__init__.py
devart/bigcommerce/bigcommerce.cp39-win32.pyd
devart/bigcommerce/bigcommerce.pyi
devart/bigcommerce/BigCommerce/Devart.Python.BigCommerceEngine.dll
devart/bigcommerce/BigCommerce/Devart.Python.BigCommerceEngine.runtimeconfig.json
devart/bigcommerce/BigCommerce/Newtonsoft.Json.dll
devart/bigcommerce/BigCommerce/System.Diagnostics.PerformanceCounter.dll
devart/bigcommerce/BigCommerce/hostfxr.dll
devart/bigcommerce/BigCommerce/sqlite3.dll
devart/bigcommerce/BigCommerce/shared/Microsoft.NETCore.App/6.0.19/.version
devart/bigcommerce/BigCommerce/shared/Microsoft.NETCore.App/6.0.19/API-MS-Win-core-xstate-l2-1-0.dll
devart/bigcommerce/BigCommerce/shared/Microsoft.NETCore.App/6.0.19/Microsoft.CSharp.dll
devart/bigcommerce/BigCommerce/shared/Microsoft.NETCore.App/6.0.19/Microsoft.DiaSymReader.Native.x86.dll
devart/bigcommerce/BigCommerce/shared/Microsoft.NETCore.App/6.0.19/Microsoft.NETCore.App.deps.json
devart/bigcommerce/BigCommerce/shared/Microsoft.NETCore.App/6.0.19/Microsoft.NETCore.App.runtimeconfig.json
devart/bigcommerce/BigCommerce/shared/Microsoft.NETCore.App/6.0.19/Microsoft.VisualBasic.Core.dll
devart/bigcommerce/BigCommerce/shared/Microsoft.NETCore.App/6.0.19/Microsoft.VisualBasic.dll
devart/bigcommerce/BigCommerce/shared/Microsoft.NETCore.App/6.0.19/Microsoft.Win32.Primitives.dll
devart/bigcommerce/BigCommerce/shared/Microsoft.NETCore.App/6.0.19/Microsoft.Win32.Registry.dll
devart/bigcommerce/BigCommerce/shared/Microsoft.NETCore.App/6.0.19/System.AppContext.dll
devart/bigcommerce/BigCommerce/shared/Microsoft.NETCore.App/6.0.19/System.Buffers.dll
devart/bigcommerce/BigCommerce/shared/Microsoft.NETCore.App/6.0.19/System.Collections.Concurrent.dll
devart/bigcommerce/BigCommerce/shared/Microsoft.NETCore.App/6.0.19/System.Collections.Immutable.dll
devart/bigcommerce/BigCommerce/shared/Microsoft.NETCore.App/6.0.19/System.Collections.NonGeneric.dll
devart_bigcommerce_connector-1.2.0.dist-info/LICENSE
devart_bigcommerce_connector-1.2.0.dist-info/METADATA
devart_bigcommerce_connector-1.2.0.dist-info/WHEEL
devart_bigcommerce_connector-1.2.0.dist-info/top_level.txt
devart_bigcommerce_connector-1.2.0.dist-info/RECORD
