Metadata-Version: 2.1
Name: devart-bigcommerce-connector
Version: 1.2.0
Summary: New level of functionality and performance in data access via Python
Home-page: https://devart.com
Author: Devart
Author-email: support@devart.com
License: Other/Proprietary License
Project-URL: Homepage, http://devart.com/python/bigcommerce
Project-URL: Download, http://devart.com/python/bigcommerce/download.html
Project-URL: History, http://devart.com/python/bigcommerce/revision_history.html
Project-URL: License, https://www.devart.com/python/eula.html
Project-URL: Documentation, http://docs.devart.com/python/bigcommerce/overview.htm
Requires-Python: >=3.7
License-File: LICENSE
